obanRAG/__init__.py
obanRAG/core.py
obanRAG-0.0.1.dist-info/LICENCE.txt
obanRAG-0.0.1.dist-info/METADATA
obanRAG-0.0.1.dist-info/WHEEL
obanRAG-0.0.1.dist-info/top_level.txt
obanRAG-0.0.1.dist-info/RECORD
