Metadata-Version: 2.1
Name: obanRAG
Version: 0.0.1
Summary: An advanced Retrieval-Augmented Generation system supporting PDF, Word, and Excel documents with feedback-based prioritization.
Author: Your Name
Author-email: volkanobn@gmail.com
Classifier: Development Status :: 4 - Beta
Classifier: Intended Audience :: End Users/Desktop
Classifier: Operating System :: OS Independent
Classifier: Programming Language :: Python :: 3
Requires-Python: >=3.7
License-File: LICENCE.txt
Requires-Dist: openai
Requires-Dist: pymupdf
Requires-Dist: pandas
Requires-Dist: python-docx
